housaku/__init__.py
housaku/cli.py
housaku/config_template.toml
housaku/db.py
housaku/feeds.py
housaku/files.py
housaku/models.py
housaku/search.py
housaku/settings.py
housaku/utils.py
housaku/commands/__init__.py
housaku/commands/config.py
housaku/commands/index.py
housaku/commands/purge.py
housaku/commands/search.py
housaku/commands/start_tui.py
housaku/commands/start_web.py
housaku/commands/vacuum.py
housaku/tui/__init__.py
housaku/tui/app.py
housaku/tui/global.tcss
housaku/web/__init__.py
housaku/web/app.py
housaku/web/index.html
housaku/web/static/alpine.min.js
housaku-0.7.12.dist-info/METADATA
housaku-0.7.12.dist-info/WHEEL
housaku-0.7.12.dist-info/entry_points.txt
housaku-0.7.12.dist-info/licenses/LICENSE
housaku-0.7.12.dist-info/RECORD
