Metadata-Version: 2.3
Name: housaku
Version: 0.7.12
Summary: A personal search engine built on top of SQLite's FTS5.
Project-URL: homepage, https://dnlzrgz.com/projects/housaku/
Project-URL: source, https://github.com/dnlzrgz/housaku
Project-URL: issues, https://github.com/dnlzrgz/housaku/issues
Project-URL: releases, https://github.com/dnlzrgz/housaku/releases
Author-email: dnlzrgz <contact@dnlzrgz.com>
License: MIT
Keywords: bm25,cli,fts,rss,rss parsing,search,search engine,sqlite,tui,web,web crawling
Classifier: Development Status :: 4 - Beta
Classifier: Environment :: Console
Classifier: Environment :: Web Environment
Classifier: Intended Audience :: Developers
Classifier: Intended Audience :: End Users/Desktop
Classifier: Intended Audience :: Information Technology
Classifier: License :: OSI Approved :: MIT License
Classifier: Natural Language :: English
Classifier: Operating System :: OS Independent
Classifier: Programming Language :: Python :: 3
Classifier: Programming Language :: Python :: 3.13
Classifier: Topic :: Database
Classifier: Topic :: Internet :: WWW/HTTP
Classifier: Topic :: Internet :: WWW/HTTP :: Indexing/Search
Classifier: Topic :: Internet :: WWW/HTTP :: WSGI :: Application
Classifier: Topic :: Text Processing
Classifier: Topic :: Utilities
Classifier: Typing :: Typed
Requires-Python: >=3.13
Requires-Dist: aiofiles>=24.1.0
Requires-Dist: aiohttp[speedups]>=3.11.7
Requires-Dist: click>=8.1.7
Requires-Dist: feedparser>=6.0.11
Requires-Dist: pydantic-settings>=2.4.0
Requires-Dist: pymupdf>=1.24.10
Requires-Dist: python-multipart>=0.0.12
Requires-Dist: rich-click>=1.8.3
Requires-Dist: rich>=13.8.0
Requires-Dist: selectolax>=0.3.21
Requires-Dist: starlette>=0.41.3
Requires-Dist: textual>=0.82.0
Requires-Dist: uvicorn>=0.32.1
